byosed/__init__.py
byosed/distributions.py
byosed/gen_BYOSED.py
byosed/perturber_io.py
byosed/perturbers.py
byosed/test_byosed.py
byosed/initfiles/BYOSED.params
byosed/initfiles/gridded_color_hsiao.dat
byosed/initfiles/gridded_hostmass_hsiao.dat
byosed/initfiles/gridded_stretch_hsiao.dat
byosed/initfiles/gridded_velocity_hsiao.dat
byosed/initfiles/host_scale.txt
byosed/initfiles/hostmass_hist_data.dat
byosed/initfiles/mangled_hsiao.dat
byosed/initfiles/salt2_colorlaw.dat
byosed/initfiles/velocity_hist_data.dat
byosed/kaepora/ejecta_velocity/SALT3_highv_N=12_Nspec=14_phase=p33.6_dm15=1.13_z=0.019.txt
byosed/kaepora/ejecta_velocity/SALT3_highv_N=13_Nspec=17_phase=p42.66_dm15=1.08_z=0.014.txt
byosed/kaepora/ejecta_velocity/SALT3_highv_N=13_Nspec=20_phase=p39.27_dm15=1.09_z=0.011.txt
byosed/kaepora/ejecta_velocity/SALT3_highv_N=14_Nspec=16_phase=p35.9_dm15=1.15_z=0.017.txt
byosed/kaepora/ejecta_velocity/SALT3_highv_N=18_Nspec=41_phase=m8.3_dm15=1.11_z=0.01.txt
byosed/kaepora/ejecta_velocity/SALT3_highv_N=19_Nspec=24_phase=p24.65_dm15=1.14_z=0.016.txt
byosed/kaepora/ejecta_velocity/SALT3_highv_N=21_Nspec=25_phase=p30.3_dm15=1.17_z=0.016.txt
byosed/kaepora/ejecta_velocity/SALT3_highv_N=22_Nspec=26_phase=p27.48_dm15=1.13_z=0.014.txt
byosed/kaepora/ejecta_velocity/SALT3_highv_N=22_Nspec=36_phase=p15.3_dm15=1.13_z=0.013.txt
byosed/kaepora/ejecta_velocity/SALT3_highv_N=23_Nspec=33_phase=p21.28_dm15=1.13_z=0.014.txt
byosed/kaepora/ejecta_velocity/SALT3_highv_N=23_Nspec=43_phase=m5.05_dm15=1.12_z=0.012.txt
byosed/kaepora/ejecta_velocity/SALT3_highv_N=25_Nspec=37_phase=p18.52_dm15=1.11_z=0.015.txt
byosed/kaepora/ejecta_velocity/SALT3_highv_N=26_Nspec=50_phase=p0.55_dm15=1.15_z=0.016.txt
byosed/kaepora/ejecta_velocity/SALT3_highv_N=26_Nspec=55_phase=p3.56_dm15=1.13_z=0.015.txt
byosed/kaepora/ejecta_velocity/SALT3_highv_N=28_Nspec=53_phase=m2.71_dm15=1.12_z=0.014.txt
byosed/kaepora/ejecta_velocity/SALT3_highv_N=30_Nspec=50_phase=p6.47_dm15=1.14_z=0.015.txt
BYOSED-0.0.3.dist-info/METADATA
BYOSED-0.0.3.dist-info/WHEEL
BYOSED-0.0.3.dist-info/top_level.txt
BYOSED-0.0.3.dist-info/RECORD
