Metadata-Version: 2.1
Name: BYOSED
Version: 0.0.3
Summary: UNKNOWN
Home-page: UNKNOWN
Author: Justin Pierel
Author-email: jr23@email.sc.edu
License: BSD
Platform: UNKNOWN
Requires-Dist: numpy (>=1.5.0)
Requires-Dist: scipy (>=0.9.0)
Requires-Dist: astropy
Requires-Dist: pytest-astropy
Requires-Dist: pandas
Requires-Dist: matplotlib
Requires-Dist: sncosmo
